targeneintersect/__init__.py
targeneintersect/targeneintersect.py
targeneintersect-0.2.4.dist-info/METADATA
targeneintersect-0.2.4.dist-info/RECORD
targeneintersect-0.2.4.dist-info/WHEEL
targeneintersect-0.2.4.dist-info/dependency_links.txt
targeneintersect-0.2.4.dist-info/top_level.txt
