Metadata-Version: 2.1
Name: targeneintersect
Version: 0.2.4
Summary: Use pybedtools intersect to gain target gene information in pandas dataframes
Home-page: https://github.com/isabelleberger/targeneintersect
Author: Isabelle Berger
Author-email: isabelle.c.berger@gmail.com
License: MIT license
Keywords: targeneintersect
Platform: UNKNOWN
Classifier: Development Status :: 2 - Pre-Alpha
Classifier: Intended Audience :: Developers
Classifier: License :: OSI Approved :: MIT License
Classifier: Natural Language :: English
Classifier: Programming Language :: Python :: 2
Classifier: Programming Language :: Python :: 2.7
Classifier: Programming Language :: Python :: 3
Classifier: Programming Language :: Python :: 3.4
Classifier: Programming Language :: Python :: 3.5
Classifier: Programming Language :: Python :: 3.6
Requires-Dist: Click (>=6.0)
Requires-Dist: pandas
Requires-Dist: pybedtools
